rosinstall_generator/__init__.py
rosinstall_generator/cli.py
rosinstall_generator/distro.py
rosinstall_generator/dry_distro.py
rosinstall_generator/generator.py
rosinstall_generator-0.1.23.dist-info/LICENSE.txt
rosinstall_generator-0.1.23.dist-info/METADATA
rosinstall_generator-0.1.23.dist-info/WHEEL
rosinstall_generator-0.1.23.dist-info/entry_points.txt
rosinstall_generator-0.1.23.dist-info/top_level.txt
rosinstall_generator-0.1.23.dist-info/RECORD
